{"code": null, "key": "edelweiss-portfolio-statement-of-bharat-bond-fof-april-2031-as-on-april-30-2026", "name": "PORTFOLIO STATEMENT OF BHARAT BOND FOF – APRIL 2031 AS ON APRIL 30, 2026", "amc": "Edelweiss Asset Management Limited", "asof": "APRIL 30, 2026", "source": "AMC monthly portfolio disclosure (SEBI Reg 59A)", "holdings": [{"name": "BHARAT BOND ETF-APRIL 2031-GROWTH", "symbol": "EBBETF0431", "isin": "INF754K01LE1", "vst_id": "VST01928", "industry": "", "pct": 99.78, "asset_class": "mf_units", "quantity": 32620092.0, "mktval_lakh": 457059.68, "maturity": null, "putcall": null}, {"name": "Clearing Corporation of India Ltd.", "symbol": null, "isin": "", "vst_id": null, "industry": "", "pct": 0.22, "asset_class": "cash", "quantity": null, "mktval_lakh": 1024.41, "maturity": null, "putcall": null}, {"name": "Net Receivables/(Payables)", "symbol": null, "isin": "", "vst_id": null, "industry": "", "pct": 0.0, "asset_class": "cash", "quantity": null, "mktval_lakh": -25.1568727, "maturity": null, "putcall": null}], "asset_alloc": {"mf_units": 99.78, "cash": 0.22}, "sector_alloc": {}, "top_holdings": [{"name": "BHARAT BOND ETF-APRIL 2031-GROWTH", "symbol": "EBBETF0431", "industry": "", "pct": 99.78, "asset_class": "mf_units"}, {"name": "Clearing Corporation of India Ltd.", "symbol": null, "industry": "", "pct": 0.22, "asset_class": "cash"}, {"name": "Net Receivables/(Payables)", "symbol": null, "industry": "", "pct": 0.0, "asset_class": "cash"}], "concentration": {"top10_pct": 100.0, "herfindahl": 0.9956, "n_holdings": 3}, "coverage": {"pct_sum": 100.0, "isin_resolved_pct": 99.8, "n_holdings": 3, "gross_exposure": false}}