{"code": null, "key": "sbi-funds-sbi-fixed-maturity-plan-fmp-series-50", "name": "SBI Fixed Maturity Plan (FMP)- Series 50", "amc": "SBI Funds Management Limited", "asof": "2026-05-31", "source": "AMC monthly portfolio disclosure (SEBI Reg 59A)", "holdings": [{"name": "6.97% CGL 2026", "symbol": null, "isin": "IN0020160035", "vst_id": null, "industry": "Sovereign", "pct": 1.16, "asset_class": "debt", "quantity": 150000.0, "mktval_lakh": 150.45, "maturity": null, "putcall": null}, {"name": "7.38% State Government of Rajasthan 2026", "symbol": null, "isin": "IN2920160156", "vst_id": null, "industry": "Sovereign", "pct": 19.29, "asset_class": "debt", "quantity": 2499900.0, "mktval_lakh": 2509.82, "maturity": null, "putcall": null}, {"name": "7.39% State Government of Uttarakhand 2026", "symbol": null, "isin": "IN3620160033", "vst_id": null, "industry": "Sovereign", "pct": 15.43, "asset_class": "debt", "quantity": 2000000.0, "mktval_lakh": 2007.96, "maturity": null, "putcall": null}, {"name": "7.37% State Government of Tamil Nadu 2026", "symbol": null, "isin": "IN3120160103", "vst_id": null, "industry": "Sovereign", "pct": 11.57, "asset_class": "debt", "quantity": 1500000.0, "mktval_lakh": 1506.17, "maturity": null, "putcall": null}, {"name": "7.62% State Government of Tamil Nadu 2026", "symbol": null, "isin": "IN3120160087", "vst_id": null, "industry": "Sovereign", "pct": 3.85, "asset_class": "debt", "quantity": 500000.0, "mktval_lakh": 501.65, "maturity": null, "putcall": null}, {"name": "6.24% State Government of Maharashtra 2026", "symbol": null, "isin": "IN2220210214", "vst_id": null, "industry": "Sovereign", "pct": 1.73, "asset_class": "debt", "quantity": 225000.0, "mktval_lakh": 225.19, "maturity": null, "putcall": null}, {"name": "91 DAY T-BILL 20.08.26", "symbol": null, "isin": "IN002026X073", "vst_id": null, "industry": "Sovereign", "pct": 3.8, "asset_class": "money_market", "quantity": 500000.0, "mktval_lakh": 494.02, "maturity": null, "putcall": null}, {"name": "GOI 22.08.2026 GOV", "symbol": null, "isin": "IN000826C023", "vst_id": null, "industry": "Sovereign", "pct": 23.04, "asset_class": "money_market", "quantity": 3035000.0, "mktval_lakh": 2998.83, "maturity": null, "putcall": null}, {"name": "GOI 12.06.2026 GOV", "symbol": null, "isin": "IN000626C043", "vst_id": null, "industry": "Sovereign", "pct": 6.19, "asset_class": "money_market", "quantity": 806300.0, "mktval_lakh": 805.03, "maturity": null, "putcall": null}, {"name": "GOI 19.09.2026 GOV", "symbol": null, "isin": "IN000926C047", "vst_id": null, "industry": "Sovereign", "pct": 6.05, "asset_class": "money_market", "quantity": 800000.0, "mktval_lakh": 787.21, "maturity": null, "putcall": null}, {"name": "GOI 15.06.2026 GOV", "symbol": null, "isin": "IN000626C050", "vst_id": null, "industry": "Sovereign", "pct": 2.49, "asset_class": "money_market", "quantity": 325000.0, "mktval_lakh": 324.35, "maturity": null, "putcall": null}, {"name": "GOI 19.06.2026 GOV", "symbol": null, "isin": "IN000626C092", "vst_id": null, "industry": "Sovereign", "pct": 2.49, "asset_class": "money_market", "quantity": 325000.0, "mktval_lakh": 324.17, "maturity": null, "putcall": null}, {"name": "GOI 17.06.2026 GOV", "symbol": null, "isin": "IN000626C035", "vst_id": null, "industry": "Sovereign", "pct": 0.77, "asset_class": "money_market", "quantity": 100000.0, "mktval_lakh": 99.77, "maturity": null, "putcall": null}, {"name": "TREPS", "symbol": null, "isin": "", "vst_id": null, "industry": "", "pct": 1.15, "asset_class": "cash", "quantity": null, "mktval_lakh": 149.83, "maturity": null, "putcall": null}, {"name": "Net Receivable / Payable", "symbol": null, "isin": "", "vst_id": null, "industry": "", "pct": 0.99, "asset_class": "cash", "quantity": null, "mktval_lakh": 129.25, "maturity": null, "putcall": null}], "asset_alloc": {"debt": 53.03, "money_market": 44.83, "cash": 2.14}, "sector_alloc": {}, "top_holdings": [{"name": "GOI 22.08.2026 GOV", "symbol": null, "industry": "Sovereign", "pct": 23.04, "asset_class": "money_market"}, {"name": "7.38% State Government of Rajasthan 2026", "symbol": null, "industry": "Sovereign", "pct": 19.29, "asset_class": "debt"}, {"name": "7.39% State Government of Uttarakhand 2026", "symbol": null, "industry": "Sovereign", "pct": 15.43, "asset_class": "debt"}, {"name": "7.37% State Government of Tamil Nadu 2026", "symbol": null, "industry": "Sovereign", "pct": 11.57, "asset_class": "debt"}, {"name": "GOI 12.06.2026 GOV", "symbol": null, "industry": "Sovereign", "pct": 6.19, "asset_class": "money_market"}, {"name": "GOI 19.09.2026 GOV", "symbol": null, "industry": "Sovereign", "pct": 6.05, "asset_class": "money_market"}, {"name": "7.62% State Government of Tamil Nadu 2026", "symbol": null, "industry": "Sovereign", "pct": 3.85, "asset_class": "debt"}, {"name": "91 DAY T-BILL 20.08.26", "symbol": null, "industry": "Sovereign", "pct": 3.8, "asset_class": "money_market"}, {"name": "GOI 15.06.2026 GOV", "symbol": null, "industry": "Sovereign", "pct": 2.49, "asset_class": "money_market"}, {"name": "GOI 19.06.2026 GOV", "symbol": null, "industry": "Sovereign", "pct": 2.49, "asset_class": "money_market"}], "concentration": {"top10_pct": 94.2, "herfindahl": 0.1399, "n_holdings": 15}, "coverage": {"pct_sum": 100.0, "isin_resolved_pct": 0, "n_holdings": 15, "gross_exposure": false}}