{"navindia_code": "41556", "scheme_name": "Mirae Asset Arbitrage Fund (G)", "amc": "Mirae Asset Mutual Fund", "sebi_category": "Arbitrage Fund", "benchmark": "NIFTY 500", "n_months": 1, "years": 0.1, "gappy": false, "is_thematic": false, "is_hybrid": true, "excess_cagr": null, "cagr_paper": null, "cagr_bench": null, "info_ratio": null, "t_stat": null, "years_needed": null, "tracking_error": null, "ic_mean": null, "ic_t": null, "sizing_edge_cum": null, "hit_rate_monthly": null, "mag_hit": null, "herfindahl": 0.0083, "herfindahl_avg": 0.0083, "eff_n": 120.9, "avg_names": 168.0, "boot_meanA_lo": null, "boot_meanA_hi": null, "boot_p_positive": null, "verdict": "insufficient history", "verdict_why": "only 1 months — no skill verdict", "basis": "GROSS holdings-implied total-return excess vs the SEBI-category benchmark (pre-cost, pre-cash-drag, pre-factor-deflation); domestic equity sleeve only, month-end snapshots. ‘Holding-rank IC’ is a cap-tilt-contaminated proxy, not pure active-weight selection (needs point-in-time benchmark weights).", "ts": [{"ym": "2025-08", "A": 0.02248, "rp": 0.03479, "rb": 0.01232, "ic": 0.0049, "n": 168}]}