{"navindia_code": "44369", "scheme_name": "WhiteOak Capital Balanced Hybrid Fund - Regular (G)", "amc": "WhiteOak Capital Mutual Fund", "sebi_category": "Balanced Hybrid Fund", "benchmark": "NIFTY 500", "n_months": 32, "years": 2.7, "gappy": false, "is_thematic": false, "is_hybrid": true, "excess_cagr": 0.0072, "cagr_paper": 0.1448, "cagr_bench": 0.1376, "info_ratio": 0.1693, "t_stat": 0.2765, "years_needed": 133.9955, "tracking_error": 0.0315, "ic_mean": 0.0154, "ic_t": 0.4653, "sizing_edge_cum": -0.1639, "hit_rate_monthly": 0.625, "mag_hit": 0.531, "slugging": 0.68, "avg_win": 0.0061, "avg_loss": -0.00898, "port_hit_cnt": 0.4835, "port_hit_aum": 0.4825, "port_slug_cnt": 0.0644, "port_slug_aum": 0.0584, "herfindahl": 0.0287, "herfindahl_avg": 0.0266, "eff_n": 34.9, "avg_names": 95.2, "boot_meanA_lo": -0.00261, "boot_meanA_hi": 0.00337, "boot_p_positive": 0.6095, "verdict": "ahead but not yet significant", "verdict_why": "+0.7%/yr, t=0.3 (need t≥2 & bootstrap≥95%; ~134y more)", "basis": "GROSS holdings-implied total-return excess vs the SEBI-category benchmark (pre-cost, pre-cash-drag, pre-factor-deflation); domestic equity sleeve only, month-end snapshots. ‘Holding-rank IC’ is a cap-tilt-contaminated proxy, not pure active-weight selection (needs point-in-time benchmark weights).", "ts": [{"ym": "2023-10", "A": -0.00413, "rp": 0.06738, "rb": 0.07151, "ic": -0.1229, "n": 81, "herf": 0.02934, "sz": -0.01608, "hc": 0.5185, "ha": 0.3847, "sc": 0.0247, "sa2": -0.0572}, {"ym": "2023-11", "A": -0.01665, "rp": 0.06348, "rb": 0.08013, "ic": 0.27, "n": 86, "herf": 0.02704, "sz": 0.01606, "hc": 0.3721, "ha": 0.4657, "sc": -0.0465, "sa2": 0.0348}, {"ym": "2023-12", "A": -0.00914, "rp": 0.01037, "rb": 0.01951, "ic": -0.0893, "n": 90, "herf": 0.02766, "sz": -0.01951, "hc": 0.5222, "ha": 0.4484, "sc": -0.2222, "sa2": -0.2792}, {"ym": "2024-01", "A": 0.01177, "rp": 0.02752, "rb": 0.01574, "ic": 0.0483, "n": 89, "herf": 0.02672, "sz": -0.00704, "hc": 0.5618, "ha": 0.5754, "sc": 0.3034, "sa2": 0.252}, {"ym": "2024-02", "A": 0.00452, "rp": 0.0129, "rb": 0.00838, "ic": 0.2929, "n": 89, "herf": 0.02659, "sz": 0.01906, "hc": 0.4382, "ha": 0.6156, "sc": 0.4045, "sa2": 0.6042}, {"ym": "2024-03", "A": -0.00483, "rp": 0.03182, "rb": 0.03665, "ic": -0.2971, "n": 85, "herf": 0.02882, "sz": -0.01779, "hc": 0.5529, "ha": 0.501, "sc": -0.3647, "sa2": -0.4534}, {"ym": "2024-04", "A": -0.00113, "rp": 0.00619, "rb": 0.00731, "ic": 0.229, "n": 91, "herf": 0.02255, "sz": 0.01114, "hc": 0.4176, "ha": 0.4687, "sc": 0.1429, "sa2": 0.1941}, {"ym": "2024-05", "A": 0.00504, "rp": 0.07555, "rb": 0.07051, "ic": -0.235, "n": 95, "herf": 0.02212, "sz": -0.01479, "hc": 0.5158, "ha": 0.4533, "sc": -0.0211, "sa2": -0.1079}, {"ym": "2024-06", "A": 0.00086, "rp": 0.04477, "rb": 0.04391, "ic": -0.2372, "n": 91, "herf": 0.02364, "sz": -0.0249, "hc": 0.5385, "ha": 0.3901, "sc": 0.044, "sa2": -0.0976}, {"ym": "2024-07", "A": 0.01889, "rp": 0.02925, "rb": 0.01036, "ic": -0.0802, "n": 87, "herf": 0.02207, "sz": -0.00572, "hc": 0.5747, "ha": 0.6237, "sc": 0.1379, "sa2": 0.1057}, {"ym": "2024-08", "A": 0.00736, "rp": 0.02903, "rb": 0.02167, "ic": -0.0157, "n": 87, "herf": 0.02169, "sz": -0.00144, "hc": 0.5747, "ha": 0.6219, "sc": 0.2299, "sa2": 0.2221}, {"ym": "2024-09", "A": 0.00865, "rp": -0.05487, "rb": -0.06352, "ic": -0.1661, "n": 84, "herf": 0.02688, "sz": -0.00996, "hc": 0.5595, "ha": 0.5332, "sc": 0.0238, "sa2": 0.0397}, {"ym": "2024-10", "A": 0.01264, "rp": 0.0131, "rb": 0.00046, "ic": 0.1457, "n": 95, "herf": 0.02132, "sz": 0.00711, "hc": 0.4421, "ha": 0.5612, "sc": 0.0421, "sa2": 0.1046}, {"ym": "2024-11", "A": 0.00219, "rp": -0.01146, "rb": -0.01366, "ic": 0.0362, "n": 95, "herf": 0.02146, "sz": -0.00425, "hc": 0.4421, "ha": 0.456, "sc": 0.0105, "sa2": 0.0343}, {"ym": "2024-12", "A": -0.01744, "rp": -0.05214, "rb": -0.0347, "ic": 0.2986, "n": 99, "herf": 0.02157, "sz": 0.01674, "hc": 0.3737, "ha": 0.5223, "sc": 0.1313, "sa2": 0.2797}, {"ym": "2025-01", "A": 0.0076, "rp": -0.07027, "rb": -0.07786, "ic": 0.203, "n": 97, "herf": 0.02262, "sz": 0.01848, "hc": 0.4124, "ha": 0.5204, "sc": 0.3402, "sa2": 0.5039}, {"ym": "2025-02", "A": 0.00186, "rp": 0.07539, "rb": 0.07353, "ic": 0.0763, "n": 96, "herf": 0.02388, "sz": -0.00126, "hc": 0.5104, "ha": 0.523, "sc": 0.1979, "sa2": 0.1403}, {"ym": "2025-03", "A": 0.00161, "rp": 0.03412, "rb": 0.03251, "ic": 0.0839, "n": 96, "herf": 0.02688, "sz": 0.00894, "hc": 0.4526, "ha": 0.5558, "sc": -0.0421, "sa2": -0.0273}, {"ym": "2025-04", "A": -0.00067, "rp": 0.03585, "rb": 0.03652, "ic": -0.3213, "n": 90, "herf": 0.03, "sz": -0.03494, "hc": 0.4944, "ha": 0.2939, "sc": -0.2247, "sa2": -0.5073}, {"ym": "2025-05", "A": -0.0103, "rp": 0.02737, "rb": 0.03767, "ic": 0.0185, "n": 91, "herf": 0.03076, "sz": -0.00754, "hc": 0.4444, "ha": 0.4976, "sc": 0.0222, "sa2": 0.0252}, {"ym": "2025-06", "A": 0.00872, "rp": -0.01955, "rb": -0.02827, "ic": -0.1034, "n": 92, "herf": 0.03087, "sz": -0.00099, "hc": 0.4835, "ha": 0.4979, "sc": -0.0549, "sa2": -0.1279}, {"ym": "2025-07", "A": 0.00596, "rp": -0.0122, "rb": -0.01817, "ic": 0.2247, "n": 96, "herf": 0.02997, "sz": 0.00095, "hc": 0.5368, "ha": 0.547, "sc": 0.2316, "sa2": 0.2369}, {"ym": "2025-08", "A": -0.00991, "rp": 0.0024, "rb": 0.01232, "ic": -0.05, "n": 98, "herf": 0.0297, "sz": -0.00255, "hc": 0.4021, "ha": 0.3513, "sc": -0.0103, "sa2": 0.0145}, {"ym": "2025-09", "A": 0.00028, "rp": 0.04394, "rb": 0.04366, "ic": 0.187, "n": 101, "herf": 0.02902, "sz": 0.00107, "hc": 0.46, "ha": 0.4425, "sc": 0.16, "sa2": 0.2323}, {"ym": "2025-10", "A": 0.00883, "rp": 0.0188, "rb": 0.00996, "ic": 0.1397, "n": 104, "herf": 0.02883, "sz": 0.00771, "hc": 0.466, "ha": 0.6203, "sc": 0.4563, "sa2": 0.6277}, {"ym": "2025-11", "A": -0.01133, "rp": -0.0139, "rb": -0.00257, "ic": 0.2316, "n": 107, "herf": 0.02888, "sz": 0.00467, "hc": 0.3019, "ha": 0.2617, "sc": 0.1509, "sa2": 0.1612}, {"ym": "2025-12", "A": 0.0012, "rp": -0.03154, "rb": -0.03273, "ic": 0.1422, "n": 108, "herf": 0.02824, "sz": 0.00962, "hc": 0.4112, "ha": 0.4437, "sc": 0.1869, "sa2": 0.268}, {"ym": "2026-01", "A": -0.01779, "rp": -0.01327, "rb": 0.00452, "ic": 0.0127, "n": 107, "herf": 0.02798, "sz": -0.00548, "hc": 0.5, "ha": 0.4611, "sc": -0.0189, "sa2": -0.0079}, {"ym": "2026-02", "A": 0.00986, "rp": -0.10379, "rb": -0.11365, "ic": 0.1092, "n": 106, "herf": 0.0288, "sz": -0.0074, "hc": 0.5714, "ha": 0.509, "sc": 0.3048, "sa2": 0.3}, {"ym": "2026-03", "A": -0.00444, "rp": 0.1008, "rb": 0.10525, "ic": -0.3184, "n": 106, "herf": 0.02695, "sz": -0.03877, "hc": 0.5094, "ha": 0.2957, "sc": -0.4528, "sa2": -0.7135}, {"ym": "2026-04", "A": 0.0005, "rp": 0.00037, "rb": -0.00013, "ic": -0.2261, "n": 103, "herf": 0.02902, "sz": -0.02589, "hc": 0.5631, "ha": 0.3534, "sc": 0.165, "sa2": 0.0251}, {"ym": "2026-05", "A": 0.00366, "rp": 0.02582, "rb": 0.02216, "ic": 0.0064, "n": 104, "herf": 0.02869, "sz": 0.00467, "hc": 0.5481, "ha": 0.6437, "sc": -0.1923, "sa2": -0.159}], "crowd_flow": {"herding_avg": 0.398, "months": ["2024-12", "2025-01", "2025-03", "2025-04", "2025-05", "2025-06", "2025-07", "2025-08", "2025-09", "2025-10", "2025-11", "2025-12", "2026-01", "2026-02", "2026-03", "2026-04", "2026-05"], "herding": [1.0, 1.0, 0.166, 0.364, 0.657, 1.0, 0.319, -0.245, 0.255, 0.651, -0.109, 0.398, 0.179, 0.35, 0.406, 0.027, 0.342], "turnover_annual": 45.9, "latest": {"buys": [{"sym": "COFORGE", "name": "Coforge Ltd", "cr": 1.2, "crowd": true}, {"sym": "LENSKART", "name": "Lenskart Solutions Ltd", "cr": 1.1, "crowd": true}, {"sym": "FIVESTAR", "name": "Five-Star Business Finance Ltd", "cr": 0.7, "crowd": true}, {"sym": "TATASTEEL", "name": "Tata Steel Ltd", "cr": 0.6, "crowd": false}, {"sym": "ICICIBANK", "name": "ICICI Bank Ltd", "cr": 0.6, "crowd": true}, {"sym": "LALPATHLAB", "name": "Dr Lal Pathlabs Ltd", "cr": 0.6, "crowd": true}], "sells": [{"sym": "CIGNITITEC", "name": "Cigniti Technologies Ltd", "cr": -1.0, "crowd": true}, {"sym": "INDIGO", "name": "Interglobe Aviation Ltd", "cr": -0.9, "crowd": false}, {"sym": "AMBUJACEM", "name": "Ambuja Cements Ltd", "cr": -0.7, "crowd": false}, {"sym": "GODREJCP", "name": "Godrej Consumer Products Ltd", "cr": -0.6, "crowd": false}, {"sym": "SBIN", "name": "State Bank of India", "cr": -0.5, "crowd": true}], "n_buys": 6, "n_sells": 5}, "ym": "2026-05", "name": "WhiteOak Capital Balanced Hybrid Fund - Regular (G)", "amc": "WhiteOak Capital Mutual Fund", "category": "Balanced Hybrid Fund", "contrarian_pctile": 8.0, "pctile_basis": "all-funds", "style": "with", "turnover_pctile": 37.0, "active_share": {"active_share": 69.6, "active_share_pctile": null, "n_peers": 1, "category": "Balanced Hybrid Fund", "cat_type": "hybrid", "ym": "2026-05", "low_confidence": true, "aum_concentrated": true, "dominant_peer": "360 ONE Balanced Hybrid Fund - Regular (G)", "dominant_share": 69.0, "predictive_validated": null, "reliable": false, "caveat": "Equity sleeve only — this fund's debt/cash allocation (often its main active lever) is not captured."}, "equity_holdings": [{"vst_id": "VST02975", "pct": 4.81, "sector": "Financial Services", "name": "ICICI Bank Ltd"}, {"vst_id": "VST02887", "pct": 3.73, "sector": "Financial Services", "name": "HDFC Bank Ltd"}, {"vst_id": "VST02300", "pct": 2.52, "sector": "Telecommunication", "name": "Bharti Airtel Ltd"}, {"vst_id": "VST03562", "pct": 1.88, "sector": "Fast Moving Consumer Goods", "name": "Nestle India Ltd"}, {"vst_id": "VST03341", "pct": 1.66, "sector": "Automobile and Auto Components", "name": "Mahindra & Mahindra Ltd"}, {"vst_id": "VST03868", "pct": 1.54, "sector": "Oil Gas & Consumable Fuels", "name": "Reliance Industries Ltd"}, {"vst_id": "VST02277", "pct": 1.38, "sector": "Capital Goods", "name": "Bharat Electronics Ltd"}, {"vst_id": "VST03264", "pct": 1.32, "sector": "Financial Services", "name": "Kotak Mahindra Bank Ltd"}, {"vst_id": "VST01377", "pct": 1.31, "sector": "Consumer Services", "name": "Zomato Ltd"}, {"vst_id": "VST03398", "pct": 1.1, "sector": "Automobile and Auto Components", "name": "Maruti Suzuki India Ltd"}, {"vst_id": "VST04296", "pct": 1.03, "sector": "Consumer Durables", "name": "Titan Company Ltd"}, {"vst_id": "VST03972", "pct": 1.0, "sector": "Financial Services", "name": "State Bank of India"}, {"vst_id": "VST03579", "pct": 0.79, "sector": "Information Technology", "name": "Coforge Ltd"}, {"vst_id": "VST02907", "pct": 0.74, "sector": "Metals & Mining", "name": "Hindalco Industries Ltd"}, {"vst_id": "VST03333", "pct": 0.66, "sector": "Construction", "name": "Larsen & Toubro Ltd"}, {"vst_id": "VST03717", "pct": 0.63, "sector": "Information Technology", "name": "Persistent Systems Ltd"}, {"vst_id": "VST03610", "pct": 0.62, "sector": "Power", "name": "NTPC Ltd"}, {"vst_id": "VST03054", "pct": 0.61, "sector": "Information Technology", "name": "Infosys Ltd"}, {"vst_id": "VST03632", "pct": 0.59, "sector": "Oil Gas & Consumable Fuels", "name": "Oil & Natural Gas Corpn Ltd"}, {"vst_id": "VST04243", "pct": 0.57, "sector": "Metals & Mining", "name": "Tata Steel Ltd"}, {"vst_id": "VST03121", "pct": 0.57, "sector": "Healthcare", "name": "J B Chemicals & Pharmaceuticals Ltd"}, {"vst_id": "VST03501", "pct": 0.55, "sector": "Financial Services", "name": "Muthoot Finance Ltd"}, {"vst_id": "VST01449", "pct": 0.53, "sector": "Capital Goods", "name": "Aditya Infotech Ltd"}, {"vst_id": "VST00933", "pct": 0.51, "sector": "Capital Goods", "name": "TD Power Systems Ltd"}, {"vst_id": "VST03243", "pct": 0.5, "sector": "Capital Goods", "name": "Kirloskar Oil Engines Ltd"}, {"vst_id": "VST01531", "pct": 0.47, "sector": "Financial Services", "name": "Aadhar Housing Finance Ltd"}, {"vst_id": "VST03409", "pct": 0.47, "sector": "Financial Services", "name": "Max Financial Services Ltd"}, {"vst_id": "VST00019", "pct": 0.46, "sector": "Healthcare", "name": "Ami Organics Ltd"}, {"vst_id": "VST04256", "pct": 0.45, "sector": "Information Technology", "name": "Tata Consultancy Services Ltd"}, {"vst_id": "VST02582", "pct": 0.45, "sector": "Capital Goods", "name": "Dynamatic Technologies Ltd"}, {"vst_id": "VST02235", "pct": 0.41, "sector": "Financial Services", "name": "Bajaj Finance Ltd"}, {"vst_id": "VST03730", "pct": 0.4, "sector": "Realty", "name": "Phoenix Mills Ltd"}, {"vst_id": "VST02229", "pct": 0.39, "sector": "Financial Services", "name": "Bajaj Finserv Ltd"}, {"vst_id": "VST03537", "pct": 0.38, "sector": "Metals & Mining", "name": "National Aluminium Company Ltd"}, {"vst_id": "VST01644", "pct": 0.38, "sector": "Healthcare", "name": "Krishna Institute of Medical Sciences Ltd"}, {"vst_id": "VST01628", "pct": 0.37, "sector": "Consumer Services", "name": "Lenskart Solutions Ltd"}, {"vst_id": "VST02439", "pct": 0.37, "sector": "Financial Services", "name": "Cholamandalam Investment & Finance Company Ltd"}, {"vst_id": "VST01582", "pct": 0.36, "sector": "Financial Services", "name": "India Shelter Finance Corporation Ltd"}, {"vst_id": "VST00112", "pct": 0.36, "sector": "Capital Goods", "name": "Azad Engineering Ltd"}, {"vst_id": "VST00925", "pct": 0.36, "sector": "Financial Services", "name": "PB Fintech Ltd"}, {"vst_id": "VST03720", "pct": 0.35, "sector": "Financial Services", "name": "Power Finance Corporation Ltd"}, {"vst_id": "VST02496", "pct": 0.35, "sector": "Capital Goods", "name": "CG Power & Industrial Solutions Ltd"}, {"vst_id": "VST02178", "pct": 0.34, "sector": "Consumer Durables", "name": "Asian Paints Ltd"}, {"vst_id": "VST04304", "pct": 0.33, "sector": "Healthcare", "name": "Torrent Pharmaceuticals Ltd"}, {"vst_id": "VST01212", "pct": 0.33, "sector": "Healthcare", "name": "Mankind Pharma Ltd"}, {"vst_id": "VST03624", "pct": 0.32, "sector": "Oil Gas & Consumable Fuels", "name": "Oil India Ltd"}, {"vst_id": "VST02145", "pct": 0.32, "sector": "Capital Goods", "name": "GE T&D India Ltd"}, {"vst_id": "VST02217", "pct": 0.31, "sector": "Financial Services", "name": "Axis Bank Ltd"}, {"vst_id": "VST01654", "pct": 0.31, "sector": "Automobile and Auto Components", "name": "Tube Investments of India Ltd"}, {"vst_id": "VST03542", "pct": 0.3, "sector": "Chemicals", "name": "Navin Fluorine International Ltd"}, {"vst_id": "VST00989", "pct": 0.3, "sector": "Financial Services", "name": "360 ONE WAM Ltd"}, {"vst_id": "VST01167", "pct": 0.29, "sector": "Financial Services", "name": "Computer Age Management Services Ltd"}, {"vst_id": "VST00286", "pct": 0.29, "sector": "Consumer Services", "name": "Schloss Bangalore Ltd"}, {"vst_id": "VST01365", "pct": 0.27, "sector": "Unclassified", "name": "CARE Ratings Ltd"}, {"vst_id": "VST00749", "pct": 0.27, "sector": "Unclassified", "name": "S J S Enterprises Ltd"}, {"vst_id": "VST00072", "pct": 0.27, "sector": "Consumer Services", "name": "Vishal Mega Mart Ltd"}, {"vst_id": "VST00737", "pct": 0.26, "sector": "Unclassified", "name": "Ajax Engineering Ltd"}, {"vst_id": "VST02058", "pct": 0.26, "sector": "Capital Goods", "name": "AIA Engineering Ltd"}, {"vst_id": "VST00527", "pct": 0.26, "sector": "Financial Services", "name": "Five-Star Business Finance Ltd"}, {"vst_id": "VST02697", "pct": 0.24, "sector": "Healthcare", "name": "Fortis Healthcare Ltd"}, {"vst_id": "VST03732", "pct": 0.24, "sector": "Chemicals", "name": "Pidilite Industries Ltd"}, {"vst_id": "VST00644", "pct": 0.24, "sector": "Healthcare", "name": "Poly Medicure Ltd"}, {"vst_id": "VST04315", "pct": 0.23, "sector": "Consumer Services", "name": "Trent Ltd"}, {"vst_id": "VST03540", "pct": 0.23, "sector": "Consumer Services", "name": "Info Edge (India) Ltd"}, {"vst_id": "VST00381", "pct": 0.23, "sector": "Consumer Durables", "name": "Eureka Forbes Ltd"}, {"vst_id": "VST00441", "pct": 0.22, "sector": "Capital Goods", "name": "KRN Heat Exchanger and Refrigeration Ltd"}, {"vst_id": "VST02094", "pct": 0.22, "sector": "Construction Materials", "name": "Ambuja Cements Ltd"}, {"vst_id": "VST02761", "pct": 0.21, "sector": "Fast Moving Consumer Goods", "name": "Gillette India Ltd"}, {"vst_id": "VST01134", "pct": 0.21, "sector": "Financial Services", "name": "PNB Housing Finance Ltd"}, {"vst_id": "VST02791", "pct": 0.2, "sector": "Fast Moving Consumer Goods", "name": "Godrej Consumer Products Ltd"}, {"vst_id": "VST04257", "pct": 0.2, "sector": "Information Technology", "name": "Tech Mahindra Ltd"}, {"vst_id": "VST01175", "pct": 0.2, "sector": "Healthcare", "name": "Dr Lal Pathlabs Ltd"}, {"vst_id": "VST02448", "pct": 0.19, "sector": "Healthcare", "name": "Cipla Ltd"}, {"vst_id": "VST01264", "pct": 0.19, "sector": "Consumer Services", "name": "TBO Tek Ltd"}, {"vst_id": "VST02499", "pct": 0.19, "sector": "Financial Services", "name": "City Union Bank Ltd"}, {"vst_id": "VST04174", "pct": 0.19, "sector": "Healthcare", "name": "Sun Pharmaceuticals Industries Ltd"}, {"vst_id": "VST02590", "pct": 0.19, "sector": "Services", "name": "eClerx Services Ltd"}, {"vst_id": "VST03568", "pct": 0.19, "sector": "Healthcare", "name": "Neuland Laboratories Ltd"}, {"vst_id": "VST00272", "pct": 0.18, "sector": "Consumer Durables", "name": "Indigo Paints Ltd"}, {"vst_id": "VST00784", "pct": 0.18, "sector": "Information Technology", "name": "Intellect Design Arena Ltd"}, {"vst_id": "VST04008", "pct": 0.17, "sector": "Healthcare", "name": "Shilpa Medicare Ltd"}, {"vst_id": "VST00519", "pct": 0.16, "sector": "Financial Services", "name": "SBI Life Insurance Company Ltd"}, {"vst_id": "VST00946", "pct": 0.15, "sector": "Consumer Durables", "name": "Safari Industries (India) Ltd"}, {"vst_id": "VST02701", "pct": 0.15, "sector": "Services", "name": "Firstsource Solutions Ltd"}, {"vst_id": "VST00657", "pct": 0.15, "sector": "Information Technology", "name": "LTIMindtree Ltd"}, {"vst_id": "VST00296", "pct": 0.14, "sector": "Chemicals", "name": "Aether Industries Ltd"}, {"vst_id": "VST03187", "pct": 0.13, "sector": "Fast Moving Consumer Goods", "name": "Jyothy Labs Ltd"}, {"vst_id": "VST02062", "pct": 0.13, "sector": "Healthcare", "name": "Ajanta Pharma Ltd"}, {"vst_id": "VST01269", "pct": 0.11, "sector": "Financial Services", "name": "CSB Bank Ltd"}, {"vst_id": "VST00364", "pct": 0.11, "sector": "Fast Moving Consumer Goods", "name": "Honasa Consumer Ltd"}, {"vst_id": "VST00775", "pct": 0.11, "sector": "Consumer Durables", "name": "Crompton Greaves Consumer Electricals Ltd"}, {"vst_id": "VST00142", "pct": 0.1, "sector": "Healthcare", "name": "Vijaya Diagnostic Centre Ltd"}, {"vst_id": "VST01632", "pct": 0.1, "sector": "Healthcare", "name": "Rainbow Childrens Medicare Ltd"}, {"vst_id": "VST03614", "pct": 0.1, "sector": "Unclassified", "name": "Nucleus Software Exports Ltd"}, {"vst_id": "VST03400", "pct": 0.09, "sector": "Information Technology", "name": "Mastek Ltd"}, {"vst_id": "VST00355", "pct": 0.09, "sector": "Information Technology", "name": "Latent View Analytics Ltd"}, {"vst_id": "VST00882", "pct": 0.08, "sector": "Unclassified", "name": "Shivalik Bimetal Controls Ltd"}, {"vst_id": "VST00495", "pct": 0.08, "sector": "Services", "name": "AWFIS Space Solutions Ltd"}, {"vst_id": "VST02019", "pct": 0.08, "sector": "Healthcare", "name": "Abbott India Ltd"}, {"vst_id": "VST00552", "pct": 0.05, "sector": "Financial Services", "name": "Cholamandalam Financial Holdings Ltd"}, {"vst_id": "VST01197", "pct": 0.04, "sector": "Information Technology", "name": "Newgen Software Technologies Ltd"}, {"vst_id": "VST00199", "pct": 0.04, "sector": "Unclassified", "name": "Indiqube Spaces Ltd"}, {"vst_id": "VST03635", "pct": 0.03, "sector": "Unclassified", "name": "Onward Technologies Ltd"}, {"vst_id": "VST00482", "pct": 0.02, "sector": "Unclassified", "name": "Laxmi Dental Ltd"}]}}