{"navindia_code": "89", "scheme_name": "Franklin India Mid Cap Fund (G)", "amc": "Franklin Templeton Mutual Fund", "sebi_category": "Mid Cap Fund", "benchmark": "NIFTY MIDCAP 100", "n_months": 151, "years": 12.6, "gappy": false, "is_thematic": false, "is_hybrid": false, "excess_cagr": 0.0258, "cagr_paper": 0.2151, "cagr_bench": 0.1893, "info_ratio": 0.3307, "t_stat": 1.173, "years_needed": 35.1353, "tracking_error": 0.0564, "ic_mean": 0.0053, "ic_t": 0.4047, "sizing_edge_cum": -0.6427, "hit_rate_monthly": 0.5298, "mag_hit": 0.5594, "herfindahl": 0.014, "herfindahl_avg": 0.0212, "eff_n": 71.3, "avg_names": 60.8, "boot_meanA_lo": -0.00104, "boot_meanA_hi": 0.00411, "boot_p_positive": 0.8845, "verdict": "ahead but not yet significant", "verdict_why": "+2.6%/yr, t=1.2 (need t≥2 & bootstrap≥95%; ~35y more)", "basis": "GROSS holdings-implied total-return excess vs the SEBI-category benchmark (pre-cost, pre-cash-drag, pre-factor-deflation); domestic equity sleeve only, month-end snapshots. ‘Holding-rank IC’ is a cap-tilt-contaminated proxy, not pure active-weight selection (needs point-in-time benchmark weights).", "ts": [{"ym": "2013-04", "A": 0.03512, "rp": 0.03597, "rb": 0.00085, "ic": 0.2066, "n": 45}, {"ym": "2013-05", "A": 0.03127, "rp": -0.02621, "rb": -0.05748, "ic": 0.2322, "n": 46}, {"ym": "2013-06", "A": 0.01505, "rp": -0.04555, "rb": -0.06061, "ic": 0.1954, "n": 44}, {"ym": "2013-07", "A": -0.0325, "rp": -0.07095, "rb": -0.03844, "ic": -0.3489, "n": 46}, {"ym": "2013-08", "A": 0.02274, "rp": 0.08574, "rb": 0.06301, "ic": 0.1199, "n": 48}, {"ym": "2013-09", "A": 0.01657, "rp": 0.09346, "rb": 0.07689, "ic": 0.1941, "n": 49}, {"ym": "2013-10", "A": 0.01684, "rp": 0.03683, "rb": 0.01999, "ic": -0.2115, "n": 50}, {"ym": "2013-11", "A": -0.00207, "rp": 0.04857, "rb": 0.05064, "ic": -0.0888, "n": 52}, {"ym": "2013-12", "A": 0.02535, "rp": -0.039, "rb": -0.06435, "ic": 0.1724, "n": 56}, {"ym": "2014-01", "A": 0.00582, "rp": 0.04309, "rb": 0.03727, "ic": -0.1399, "n": 55}, {"ym": "2014-02", "A": 0.01331, "rp": 0.11725, "rb": 0.10394, "ic": -0.07, "n": 58}, {"ym": "2014-03", "A": 0.00182, "rp": 0.02184, "rb": 0.02001, "ic": -0.0849, "n": 57}, {"ym": "2014-04", "A": -0.01556, "rp": 0.1395, "rb": 0.15506, "ic": -0.1326, "n": 57}, {"ym": "2014-05", "A": 0.00775, "rp": 0.10275, "rb": 0.09501, "ic": -0.1307, "n": 58}, {"ym": "2014-06", "A": 0.03153, "rp": 0.01179, "rb": -0.01975, "ic": -0.0306, "n": 58}, {"ym": "2014-07", "A": 0.0284, "rp": 0.05597, "rb": 0.02758, "ic": 0.1108, "n": 59}, {"ym": "2014-08", "A": 0.01988, "rp": 0.0486, "rb": 0.02872, "ic": -0.0467, "n": 58}, {"ym": "2014-09", "A": 0.00996, "rp": 0.04706, "rb": 0.03709, "ic": 0.127, "n": 61}, {"ym": "2014-10", "A": 0.01445, "rp": 0.06085, "rb": 0.0464, "ic": 0.2964, "n": 60}, {"ym": "2014-11", "A": 0.03432, "rp": 0.05002, "rb": 0.01571, "ic": 0.29, "n": 60}, {"ym": "2014-12", "A": 0.01596, "rp": 0.05937, "rb": 0.04341, "ic": 0.1024, "n": 59}, {"ym": "2015-01", "A": 0.00503, "rp": 0.0051, "rb": 7e-05, "ic": 0.1055, "n": 57}, {"ym": "2015-02", "A": -0.00205, "rp": -0.01016, "rb": -0.00811, "ic": 0.0557, "n": 57}, {"ym": "2015-03", "A": -0.00428, "rp": -0.02812, "rb": -0.02385, "ic": -0.0951, "n": 59}, {"ym": "2015-04", "A": 0.00235, "rp": 0.04156, "rb": 0.03921, "ic": -0.0816, "n": 59}, {"ym": "2015-05", "A": 0.00335, "rp": -0.0086, "rb": -0.01196, "ic": 0.0228, "n": 59}, {"ym": "2015-06", "A": -0.01252, "rp": 0.04581, "rb": 0.05833, "ic": -0.0515, "n": 57}, {"ym": "2015-07", "A": -0.00706, "rp": -0.05492, "rb": -0.04786, "ic": 0.0091, "n": 57}, {"ym": "2015-08", "A": 0.00592, "rp": 0.00249, "rb": -0.00342, "ic": 0.0338, "n": 57}, {"ym": "2015-09", "A": -0.006, "rp": 0.01381, "rb": 0.01981, "ic": -0.0867, "n": 57}, {"ym": "2015-10", "A": 0.00599, "rp": 0.00712, "rb": 0.00113, "ic": -0.1209, "n": 57}, {"ym": "2015-11", "A": -0.00566, "rp": 0.00602, "rb": 0.01168, "ic": 0.0801, "n": 56}, {"ym": "2015-12", "A": 0.01167, "rp": -0.05726, "rb": -0.06894, "ic": 0.2416, "n": 58}, {"ym": "2016-01", "A": -0.00457, "rp": -0.07582, "rb": -0.07125, "ic": -0.0357, "n": 58}, {"ym": "2016-02", "A": 0.00066, "rp": 0.10659, "rb": 0.10593, "ic": 0.0867, "n": 57}, {"ym": "2016-03", "A": 0.0047, "rp": 0.03961, "rb": 0.0349, "ic": 0.0445, "n": 57}, {"ym": "2016-04", "A": 0.03155, "rp": 0.03895, "rb": 0.0074, "ic": 0.0356, "n": 57}, {"ym": "2016-05", "A": 0.01161, "rp": 0.05145, "rb": 0.03984, "ic": -0.1173, "n": 57}, {"ym": "2016-06", "A": -0.0241, "rp": 0.04682, "rb": 0.07092, "ic": 0.134, "n": 56}, {"ym": "2016-07", "A": -0.00026, "rp": 0.04234, "rb": 0.04261, "ic": -0.0579, "n": 54}, {"ym": "2016-08", "A": -0.0122, "rp": -0.00831, "rb": 0.0039, "ic": 0.0913, "n": 53}, {"ym": "2016-09", "A": -0.00206, "rp": 0.03073, "rb": 0.03279, "ic": -0.0358, "n": 54}, {"ym": "2016-10", "A": -0.01633, "rp": -0.07896, "rb": -0.06263, "ic": -0.2804, "n": 56}, {"ym": "2016-11", "A": 0.01485, "rp": -0.02243, "rb": -0.03727, "ic": 0.1576, "n": 57}, {"ym": "2016-12", "A": -0.00259, "rp": 0.07237, "rb": 0.07496, "ic": -0.0561, "n": 57}, {"ym": "2017-01", "A": -0.01066, "rp": 0.06059, "rb": 0.07125, "ic": 0.1132, "n": 58}, {"ym": "2017-02", "A": 0.007, "rp": 0.05332, "rb": 0.04632, "ic": -0.132, "n": 57}, {"ym": "2017-03", "A": -0.00711, "rp": 0.04534, "rb": 0.05245, "ic": -0.2682, "n": 61}, {"ym": "2017-04", "A": 0.0254, "rp": -0.00596, "rb": -0.03136, "ic": -0.1172, "n": 61}, {"ym": "2017-05", "A": -0.0172, "rp": -0.00405, "rb": 0.01315, "ic": -0.3467, "n": 60}, {"ym": "2017-06", "A": -0.00277, "rp": 0.04361, "rb": 0.04638, "ic": 0.0993, "n": 60}, {"ym": "2017-07", "A": 0.0069, "rp": -0.00459, "rb": -0.01149, "ic": 0.1564, "n": 59}, {"ym": "2017-08", "A": 0.00923, "rp": 0.0015, "rb": -0.00773, "ic": -0.1005, "n": 60}, {"ym": "2017-09", "A": -0.03662, "rp": 0.04468, "rb": 0.0813, "ic": -0.1877, "n": 61}, {"ym": "2017-10", "A": 0.01686, "rp": 0.03442, "rb": 0.01755, "ic": -0.0014, "n": 62}, {"ym": "2017-11", "A": -0.0116, "rp": 0.05065, "rb": 0.06224, "ic": -0.1101, "n": 60}, {"ym": "2017-12", "A": 0.00515, "rp": -0.01123, "rb": -0.01638, "ic": -0.0576, "n": 59}, {"ym": "2018-01", "A": 0.0285, "rp": -0.02412, "rb": -0.05262, "ic": 0.2152, "n": 59}, {"ym": "2018-02", "A": 0.01786, "rp": -0.02721, "rb": -0.04508, "ic": 0.0661, "n": 58}, {"ym": "2018-03", "A": -0.03159, "rp": 0.05049, "rb": 0.08208, "ic": -0.102, "n": 58}, {"ym": "2018-04", "A": 0.04802, "rp": -0.02021, "rb": -0.06823, "ic": 0.1978, "n": 59}, {"ym": "2018-05", "A": -0.00772, "rp": -0.04534, "rb": -0.03763, "ic": 0.0264, "n": 58}, {"ym": "2018-06", "A": 0.00133, "rp": 0.04249, "rb": 0.04116, "ic": 0.0671, "n": 57}, {"ym": "2018-07", "A": -0.02138, "rp": 0.03514, "rb": 0.05652, "ic": -0.0735, "n": 56}, {"ym": "2018-08", "A": 0.03007, "rp": -0.10798, "rb": -0.13805, "ic": 0.0609, "n": 56}, {"ym": "2018-09", "A": -0.015, "rp": -0.01277, "rb": 0.00223, "ic": -0.2071, "n": 57}, {"ym": "2018-10", "A": 0.01465, "rp": 0.03384, "rb": 0.01919, "ic": 0.2304, "n": 59}, {"ym": "2018-11", "A": 0.0047, "rp": 0.02595, "rb": 0.02125, "ic": 0.0128, "n": 62}, {"ym": "2018-12", "A": 0.03033, "rp": -0.02389, "rb": -0.05421, "ic": -0.0292, "n": 60}, {"ym": "2019-01", "A": 0.00999, "rp": 0.00011, "rb": -0.00988, "ic": 0.151, "n": 60}, {"ym": "2019-02", "A": -0.01059, "rp": 0.08142, "rb": 0.09201, "ic": -0.0196, "n": 60}, {"ym": "2019-03", "A": 0.00909, "rp": -0.02859, "rb": -0.03768, "ic": 0.4017, "n": 61}, {"ym": "2019-04", "A": 0.0034, "rp": 0.02628, "rb": 0.02287, "ic": 0.2862, "n": 62}, {"ym": "2019-05", "A": 0.00645, "rp": -0.00966, "rb": -0.0161, "ic": 0.2336, "n": 62}, {"ym": "2019-06", "A": 0.02516, "rp": -0.0698, "rb": -0.09496, "ic": 0.0971, "n": 61}, {"ym": "2019-07", "A": 0.00713, "rp": -0.00804, "rb": -0.01517, "ic": 0.2679, "n": 60}, {"ym": "2019-08", "A": 0.03059, "rp": 0.05533, "rb": 0.02474, "ic": 0.07, "n": 60}, {"ym": "2019-09", "A": -0.01717, "rp": 0.03247, "rb": 0.04964, "ic": -0.0364, "n": 61}, {"ym": "2019-10", "A": -0.01425, "rp": 0.01027, "rb": 0.02452, "ic": 0.0695, "n": 62}, {"ym": "2019-11", "A": 0.00053, "rp": -0.00637, "rb": -0.00689, "ic": -0.2013, "n": 62}, {"ym": "2019-12", "A": -0.01859, "rp": 0.03448, "rb": 0.05308, "ic": -0.0253, "n": 61}, {"ym": "2020-01", "A": 0.01901, "rp": -0.04706, "rb": -0.06607, "ic": 0.2128, "n": 60}, {"ym": "2020-02", "A": 0.01694, "rp": -0.28412, "rb": -0.30105, "ic": 0.0246, "n": 61}, {"ym": "2020-03", "A": -0.02082, "rp": 0.13283, "rb": 0.15364, "ic": -0.1156, "n": 61}, {"ym": "2020-04", "A": -0.01641, "rp": -0.03337, "rb": -0.01696, "ic": 0.0832, "n": 59}, {"ym": "2020-05", "A": -0.00256, "rp": 0.10596, "rb": 0.10852, "ic": -0.4001, "n": 58}, {"ym": "2020-06", "A": -0.02795, "rp": 0.02579, "rb": 0.05374, "ic": -0.1303, "n": 53}, {"ym": "2020-07", "A": 0.01071, "rp": 0.08962, "rb": 0.0789, "ic": -0.3883, "n": 53}, {"ym": "2020-08", "A": -0.02947, "rp": -0.01034, "rb": 0.01913, "ic": 0.1692, "n": 50}, {"ym": "2020-09", "A": 0.02626, "rp": 0.03125, "rb": 0.00499, "ic": -0.0421, "n": 50}, {"ym": "2020-10", "A": -0.00806, "rp": 0.14832, "rb": 0.15638, "ic": 0.0144, "n": 48}, {"ym": "2020-11", "A": -0.0112, "rp": 0.04606, "rb": 0.05726, "ic": -0.0728, "n": 49}, {"ym": "2020-12", "A": -0.00384, "rp": -0.00055, "rb": 0.00329, "ic": -0.0885, "n": 50}, {"ym": "2021-01", "A": -0.00073, "rp": 0.11358, "rb": 0.11431, "ic": -0.1193, "n": 51}, {"ym": "2021-02", "A": -0.0164, "rp": 0.00274, "rb": 0.01914, "ic": -0.3142, "n": 49}, {"ym": "2021-03", "A": -0.01849, "rp": 0.00332, "rb": 0.02181, "ic": 0.1524, "n": 50}, {"ym": "2021-04", "A": -0.0002, "rp": 0.06544, "rb": 0.06563, "ic": -0.3264, "n": 49}, {"ym": "2021-05", "A": -0.00133, "rp": 0.04593, "rb": 0.04726, "ic": -0.2938, "n": 49}, {"ym": "2021-06", "A": 0.00789, "rp": 0.04044, "rb": 0.03255, "ic": 0.2207, "n": 49}, {"ym": "2021-07", "A": 0.00714, "rp": 0.02997, "rb": 0.02283, "ic": 0.1756, "n": 48}, {"ym": "2021-08", "A": -0.02421, "rp": 0.04664, "rb": 0.07085, "ic": -0.0692, "n": 51}, {"ym": "2021-09", "A": -0.00122, "rp": 0.00172, "rb": 0.00295, "ic": 0.0573, "n": 50}, {"ym": "2021-10", "A": -0.00986, "rp": -0.03499, "rb": -0.02513, "ic": -0.2986, "n": 50}, {"ym": "2021-11", "A": -0.01919, "rp": 0.00753, "rb": 0.02672, "ic": -0.2406, "n": 51}, {"ym": "2021-12", "A": -0.00188, "rp": -0.00741, "rb": -0.00553, "ic": -0.0968, "n": 54}, {"ym": "2022-01", "A": 0.00956, "rp": -0.05577, "rb": -0.06534, "ic": 0.1113, "n": 56}, {"ym": "2022-02", "A": -0.02805, "rp": 0.02444, "rb": 0.05249, "ic": -0.1392, "n": 60}, {"ym": "2022-03", "A": -0.0014, "rp": 0.00495, "rb": 0.00635, "ic": 0.0829, "n": 62}, {"ym": "2022-04", "A": -0.00706, "rp": -0.06017, "rb": -0.05311, "ic": -0.0781, "n": 64}, {"ym": "2022-05", "A": 0.01579, "rp": -0.0473, "rb": -0.06309, "ic": 0.0823, "n": 64}, {"ym": "2022-06", "A": 0.00189, "rp": 0.12449, "rb": 0.1226, "ic": 0.1459, "n": 64}, {"ym": "2022-07", "A": -0.01335, "rp": 0.0503, "rb": 0.06365, "ic": 0.0643, "n": 65}, {"ym": "2022-08", "A": 0.0297, "rp": 0.00494, "rb": -0.02476, "ic": 0.0766, "n": 65}, {"ym": "2022-09", "A": 0.00255, "rp": 0.02755, "rb": 0.025, "ic": 0.156, "n": 65}, {"ym": "2022-10", "A": -0.00774, "rp": 0.01196, "rb": 0.0197, "ic": -0.2678, "n": 66}, {"ym": "2022-11", "A": -0.00668, "rp": -0.02319, "rb": -0.01651, "ic": -0.1758, "n": 67}, {"ym": "2022-12", "A": 0.00174, "rp": -0.02431, "rb": -0.02605, "ic": 0.2214, "n": 66}, {"ym": "2023-01", "A": 0.00521, "rp": -0.01217, "rb": -0.01738, "ic": 0.0141, "n": 66}, {"ym": "2023-02", "A": -0.00362, "rp": -0.00623, "rb": -0.0026, "ic": 0.091, "n": 66}, {"ym": "2023-03", "A": -0.02276, "rp": 0.03583, "rb": 0.05858, "ic": -0.1756, "n": 67}, {"ym": "2023-04", "A": 0.00099, "rp": 0.06296, "rb": 0.06197, "ic": 0.0636, "n": 68}, {"ym": "2023-05", "A": -0.00265, "rp": 0.05784, "rb": 0.06049, "ic": 0.0269, "n": 67}, {"ym": "2023-06", "A": -0.01195, "rp": 0.04455, "rb": 0.0565, "ic": -0.0934, "n": 69}, {"ym": "2023-07", "A": -0.01062, "rp": 0.0275, "rb": 0.03812, "ic": 0.0351, "n": 68}, {"ym": "2023-08", "A": -0.02496, "rp": 0.01152, "rb": 0.03648, "ic": -0.034, "n": 68}, {"ym": "2023-09", "A": 0.01684, "rp": -0.02404, "rb": -0.04088, "ic": -0.0144, "n": 67}, {"ym": "2023-10", "A": -0.00765, "rp": 0.09727, "rb": 0.10492, "ic": 0.1179, "n": 70}, {"ym": "2023-11", "A": -0.00445, "rp": 0.07182, "rb": 0.07627, "ic": 0.2864, "n": 69}, {"ym": "2023-12", "A": -0.02519, "rp": 0.02661, "rb": 0.05179, "ic": -0.0711, "n": 71}, {"ym": "2024-01", "A": 0.01407, "rp": 0.01034, "rb": -0.00373, "ic": 0.1684, "n": 70}, {"ym": "2024-02", "A": 0.00089, "rp": -0.00412, "rb": -0.005, "ic": 0.078, "n": 70}, {"ym": "2024-03", "A": 0.00805, "rp": 0.06616, "rb": 0.05812, "ic": -0.0083, "n": 71}, {"ym": "2024-04", "A": 0.01725, "rp": 0.03386, "rb": 0.01661, "ic": 0.1841, "n": 71}, {"ym": "2024-05", "A": 0.02313, "rp": 0.10216, "rb": 0.07903, "ic": -0.0008, "n": 71}, {"ym": "2024-06", "A": -0.00963, "rp": 0.0496, "rb": 0.05923, "ic": 0.0794, "n": 72}, {"ym": "2024-07", "A": 0.01548, "rp": 0.02129, "rb": 0.00581, "ic": 0.0399, "n": 73}, {"ym": "2024-08", "A": 0.005, "rp": 0.02, "rb": 0.015, "ic": -0.0963, "n": 74}, {"ym": "2024-09", "A": 0.02023, "rp": -0.04684, "rb": -0.06708, "ic": 0.2202, "n": 76}, {"ym": "2024-10", "A": 0.00524, "rp": 0.01076, "rb": 0.00551, "ic": 0.1631, "n": 76}, {"ym": "2024-11", "A": -0.00495, "rp": 0.00936, "rb": 0.01431, "ic": 0.1406, "n": 76}, {"ym": "2024-12", "A": -0.01309, "rp": -0.07387, "rb": -0.06079, "ic": -0.226, "n": 79}, {"ym": "2025-01", "A": 0.01232, "rp": -0.09481, "rb": -0.10713, "ic": 0.0742, "n": 78}, {"ym": "2025-02", "A": 0.00157, "rp": 0.08004, "rb": 0.07847, "ic": -0.0262, "n": 80}, {"ym": "2025-03", "A": -0.01878, "rp": 0.02881, "rb": 0.04759, "ic": -0.0712, "n": 81}, {"ym": "2025-04", "A": -0.01504, "rp": 0.04654, "rb": 0.06158, "ic": -0.1391, "n": 80}, {"ym": "2025-05", "A": 0.00752, "rp": 0.04861, "rb": 0.04109, "ic": 0.2515, "n": 80}, {"ym": "2025-06", "A": 0.01631, "rp": -0.0219, "rb": -0.03821, "ic": -0.0164, "n": 84}, {"ym": "2025-07", "A": 0.00384, "rp": -0.02446, "rb": -0.0283, "ic": -0.2711, "n": 85}, {"ym": "2025-08", "A": -0.01832, "rp": -0.00357, "rb": 0.01475, "ic": -0.2289, "n": 86}, {"ym": "2025-09", "A": -0.01178, "rp": 0.04666, "rb": 0.05844, "ic": 0.1734, "n": 86}, {"ym": "2025-10", "A": -0.01483, "rp": 0.00641, "rb": 0.02124, "ic": 0.0201, "n": 86}], "portfolio": {"asof": "2025-10-31", "n_equity": 86, "equity_pct_fund": 96.6, "asset_alloc": {"Equity": 96.6}, "sector_cover": 98.5, "sector_now": [{"sector": "Financial Services", "pct": 21.8}, {"sector": "Capital Goods", "pct": 12.5}, {"sector": "Healthcare", "pct": 10.0}, {"sector": "Automobile and Auto Components", "pct": 6.7}, {"sector": "Realty", "pct": 6.6}, {"sector": "Chemicals", "pct": 6.3}, {"sector": "Information Technology", "pct": 6.1}, {"sector": "Consumer Services", "pct": 5.3}, {"sector": "Consumer Durables", "pct": 5.1}, {"sector": "Telecommunication", "pct": 4.0}, {"sector": "Fast Moving Consumer Goods", "pct": 3.7}, {"sector": "Construction Materials", "pct": 3.7}, {"sector": "Textiles", "pct": 2.3}, {"sector": "Metals & Mining", "pct": 1.6}, {"sector": "Unclassified", "pct": 1.5}, {"sector": "Oil Gas & Consumable Fuels", "pct": 1.2}, {"sector": "Power", "pct": 1.1}, {"sector": "Services", "pct": 0.7}], "top_holdings": [{"name": "Federal Bank Ltd", "symbol": "FEDERALBNK", "pct": 3.02, "sector": "Financial Services", "vst_id": "VST02680"}, {"name": "Cummins India Ltd", "symbol": "CUMMINSIND", "pct": 2.44, "sector": "Capital Goods", "vst_id": "VST02501"}, {"name": "Mphasis Ltd", "symbol": "MPHASIS", "pct": 2.28, "sector": "Information Technology", "vst_id": "VST03475"}, {"name": "Prestige Estates Projects Ltd", "symbol": "PRESTIGE", "pct": 2.23, "sector": "Realty", "vst_id": "VST03775"}, {"name": "Mahindra & Mahindra Financial Services Ltd", "symbol": "M&MFIN", "pct": 2.13, "sector": "Financial Services", "vst_id": "VST03342"}, {"name": "APL Apollo Tubes Ltd", "symbol": "APLAPOLLO", "pct": 2.1, "sector": "Capital Goods", "vst_id": "VST01292"}, {"name": "IDFC First Bank Ltd", "symbol": "IDFCFIRSTB", "pct": 1.85, "sector": "Financial Services", "vst_id": "VST00253"}, {"name": "PB Fintech Ltd", "symbol": "POLICYBZR", "pct": 1.82, "sector": "Financial Services", "vst_id": "VST00925"}, {"name": "Biocon Ltd", "symbol": "BIOCON", "pct": 1.71, "sector": "Healthcare", "vst_id": "VST02318"}, {"name": "Coforge Ltd", "symbol": "COFORGE", "pct": 1.69, "sector": "Information Technology", "vst_id": "VST03579"}, {"name": "J K Cements Ltd", "symbol": "JKCEMENT", "pct": 1.64, "sector": "Construction Materials", "vst_id": "VST03154"}, {"name": "Ipca Laboratories Ltd", "symbol": "IPCALAB", "pct": 1.62, "sector": "Healthcare", "vst_id": "VST03075"}, {"name": "Tata Steel Ltd", "symbol": "TATASTEEL", "pct": 1.55, "sector": "Metals & Mining", "vst_id": "VST04243"}, {"name": "Bharti Hexacom Ltd", "symbol": "BHARTIHEXA", "pct": 1.54, "sector": "Telecommunication", "vst_id": "VST00829"}, {"name": "Max Financial Services Ltd", "symbol": "MFSL", "pct": 1.52, "sector": "Financial Services", "vst_id": "VST03409"}], "by_sector": [{"sector": "Financial Services", "pct": 21.06, "names": [{"name": "Federal Bank Ltd", "symbol": "FEDERALBNK", "pct": 3.02}, {"name": "Mahindra & Mahindra Financial Services Ltd", "symbol": "M&MFIN", "pct": 2.13}, {"name": "IDFC First Bank Ltd", "symbol": "IDFCFIRSTB", "pct": 1.85}, {"name": "PB Fintech Ltd", "symbol": "POLICYBZR", "pct": 1.82}, {"name": "Max Financial Services Ltd", "symbol": "MFSL", "pct": 1.52}, {"name": "HDFC Bank Ltd", "symbol": "HDFCBANK", "pct": 1.5}, {"name": "ICICI Lombard General Insurance Company Ltd", "symbol": "ICICIGI", "pct": 1.33}, {"name": "City Union Bank Ltd", "symbol": "CUB", "pct": 1.19}, {"name": "SBI Cards & Payment Services Ltd", "symbol": "SBICARD", "pct": 1.17}, {"name": "Equitas Small Finance Bank Ltd", "symbol": "EQUITASBNK", "pct": 1.05}, {"name": "PNB Housing Finance Ltd", "symbol": "PNBHOUSING", "pct": 1.02}, {"name": "State Bank of India", "symbol": "SBIN", "pct": 0.98}, {"name": "L&T Finance Ltd", "symbol": "LTF", "pct": 0.74}, {"name": "HDB Financial Services Ltd", "symbol": "HDBFS", "pct": 0.7}, {"name": "REC Ltd", "symbol": "RECLTD", "pct": 0.65}, {"name": "Angel One Ltd", "symbol": "ANGELONE", "pct": 0.39}]}, {"sector": "Capital Goods", "pct": 12.1, "names": [{"name": "Cummins India Ltd", "symbol": "CUMMINSIND", "pct": 2.44}, {"name": "APL Apollo Tubes Ltd", "symbol": "APLAPOLLO", "pct": 2.1}, {"name": "Escorts Kubota Ltd", "symbol": "ESCORTS", "pct": 1.41}, {"name": "Bharat Electronics Ltd", "symbol": "BEL", "pct": 1.12}, {"name": "CG Power & Industrial Solutions Ltd", "symbol": "CGPOWER", "pct": 1.06}, {"name": "Astral Ltd", "symbol": "ASTRAL", "pct": 0.88}, {"name": "Hindustan Aeronautics Ltd", "symbol": "HAL", "pct": 0.76}, {"name": "Ashok Leyland Ltd", "symbol": "ASHOKLEY", "pct": 0.67}, {"name": "Timken India Ltd", "symbol": "TIMKEN", "pct": 0.63}, {"name": "Siemens Energy India Ltd", "symbol": "ENRIN", "pct": 0.56}, {"name": "Suzlon Energy Ltd", "symbol": "SUZLON", "pct": 0.46}]}, {"sector": "Healthcare", "pct": 9.61, "names": [{"name": "Biocon Ltd", "symbol": "BIOCON", "pct": 1.71}, {"name": "Ipca Laboratories Ltd", "symbol": "IPCALAB", "pct": 1.62}, {"name": "Aster DM Healthcare Ltd", "symbol": "ASTERDM", "pct": 1.28}, {"name": "Abbott India Ltd", "symbol": "ABBOTINDIA", "pct": 1.19}, {"name": "Apollo Hospitals Enterprise Ltd", "symbol": "APOLLOHOSP", "pct": 1.08}, {"name": "Alkem Laboratories Ltd", "symbol": "ALKEM", "pct": 1.01}, {"name": "Ajanta Pharma Ltd", "symbol": "AJANTPHARM", "pct": 0.76}, {"name": "Max Healthcare Institute Ltd", "symbol": "MAXHEALTH", "pct": 0.74}, {"name": "Anthem Biosciences Ltd", "symbol": "ANTHEM", "pct": 0.23}]}, {"sector": "Automobile and Auto Components", "pct": 6.42, "names": [{"name": "Tube Investments of India Ltd", "symbol": "TIINDIA", "pct": 1.28}, {"name": "Balkrishna Industries Ltd", "symbol": "BALKRISIND", "pct": 1.25}, {"name": "Motherson Sumi Wiring India Ltd", "symbol": "MSUMI", "pct": 0.97}, {"name": "Exide Industries Ltd", "symbol": "EXIDEIND", "pct": 0.84}, {"name": "Hero MotoCorp Ltd", "symbol": "HEROMOTOCO", "pct": 0.61}, {"name": "Uno Minda Ltd", "symbol": "UNOMINDA", "pct": 0.55}, {"name": "Apollo Tyres Ltd", "symbol": "APOLLOTYRE", "pct": 0.47}, {"name": "ZF Commercial Vehicle Control System India Ltd", "symbol": "ZFCVINDIA", "pct": 0.45}]}, {"sector": "Realty", "pct": 6.38, "names": [{"name": "Prestige Estates Projects Ltd", "symbol": "PRESTIGE", "pct": 2.23}, {"name": "Phoenix Mills Ltd", "symbol": "PHOENIXLTD", "pct": 1.49}, {"name": "Oberoi Realty Ltd", "symbol": "OBEROIRLTY", "pct": 1.36}, {"name": "Godrej Properties Ltd", "symbol": "GODREJPROP", "pct": 1.3}]}, {"sector": "Chemicals", "pct": 6.08, "names": [{"name": "Deepak Nitrite Ltd", "symbol": "DEEPAKNTR", "pct": 1.49}, {"name": "UPL Ltd", "symbol": "UPL", "pct": 1.37}, {"name": "SRF Ltd", "symbol": "SRF", "pct": 1.22}, {"name": "P I Industries Ltd", "symbol": "PIIND", "pct": 1.05}, {"name": "Coromandel International Ltd", "symbol": "COROMANDEL", "pct": 0.96}]}, {"sector": "Information Technology", "pct": 5.91, "names": [{"name": "Mphasis Ltd", "symbol": "MPHASIS", "pct": 2.28}, {"name": "Coforge Ltd", "symbol": "COFORGE", "pct": 1.69}, {"name": "Persistent Systems Ltd", "symbol": "PERSISTENT", "pct": 1.24}, {"name": "Hexaware Technologies Ltd", "symbol": "HEXT", "pct": 0.7}]}, {"sector": "Consumer Services", "pct": 5.12, "names": [{"name": "Trent Ltd", "symbol": "TRENT", "pct": 1.08}, {"name": "ITC Hotels Ltd", "symbol": "ITCHOTELS", "pct": 0.88}, {"name": "Jubilant Foodworks Ltd", "symbol": "JUBLFOOD", "pct": 0.86}, {"name": "Indian Hotels Co Ltd", "symbol": "INDHOTEL", "pct": 0.84}, {"name": "Vishal Mega Mart Ltd", "symbol": "VMM", "pct": 0.69}, {"name": "Devyani International Ltd", "symbol": "DEVYANI", "pct": 0.66}, {"name": "Lenskart Solutions Ltd", "symbol": "LENSKART", "pct": 0.1}]}, {"sector": "Consumer Durables", "pct": 4.93, "names": [{"name": "Kalyan Jewellers India Ltd", "symbol": "KALYANKJIL", "pct": 1.42}, {"name": "Crompton Greaves Consumer Electricals Ltd", "symbol": "CROMPTON", "pct": 1.41}, {"name": "Dixon Technologies (India) Ltd", "symbol": "DIXON", "pct": 1.16}, {"name": "LG Electronics India Ltd", "symbol": "LGEINDIA", "pct": 0.47}, {"name": "Kajaria Ceramics Ltd", "symbol": "KAJARIACER", "pct": 0.47}]}, {"sector": "Telecommunication", "pct": 3.82, "names": [{"name": "Bharti Hexacom Ltd", "symbol": "BHARTIHEXA", "pct": 1.54}, {"name": "Tata Communications Ltd", "symbol": "TATACOMM", "pct": 1.3}, {"name": "Indus Towers Ltd", "symbol": "INDUSTOWER", "pct": 0.98}]}, {"sector": "Fast Moving Consumer Goods", "pct": 3.57, "names": [{"name": "Emami Ltd", "symbol": "EMAMILTD", "pct": 1.39}, {"name": "United Breweries Ltd", "symbol": "UBL", "pct": 1.17}, {"name": "Marico Ltd", "symbol": "MARICO", "pct": 1.01}]}, {"sector": "Construction Materials", "pct": 3.53, "names": [{"name": "J K Cements Ltd", "symbol": "JKCEMENT", "pct": 1.64}, {"name": "The Ramco Cements Ltd", "symbol": "RAMCOCEM", "pct": 1.05}, {"name": "ACC Ltd", "symbol": "ACC", "pct": 0.84}]}, {"sector": "Textiles", "pct": 2.25, "names": [{"name": "Page Industries Ltd", "symbol": "PAGEIND", "pct": 1.24}, {"name": "K P R Mill Ltd", "symbol": "KPRMILL", "pct": 1.0}]}, {"sector": "Metals & Mining", "pct": 1.55, "names": [{"name": "Tata Steel Ltd", "symbol": "TATASTEEL", "pct": 1.55}]}, {"sector": "Unclassified", "pct": 1.41, "names": [{"name": "Procter & Gamble Hygiene and Health Care Ltd", "symbol": "PGHH", "pct": 0.93}, {"name": "Sundram Fasteners Ltd", "symbol": "SUNDRMFAST", "pct": 0.48}]}, {"sector": "Oil Gas & Consumable Fuels", "pct": 1.15, "names": [{"name": "Hindustan Petroleum Corporation Ltd", "symbol": "HINDPETRO", "pct": 1.15}]}, {"sector": "Power", "pct": 1.01, "names": [{"name": "Tata Power Company Ltd", "symbol": "TATAPOWER", "pct": 1.01}]}, {"sector": "Services", "pct": 0.65, "names": [{"name": "Container Corporation Of India Ltd", "symbol": "CONCOR", "pct": 0.65}]}], "rotation": {"dates": ["2013-09", "2014-03", "2014-09", "2015-03", "2015-09", "2016-03", "2016-09", "2017-03", "2017-09", "2018-03", "2018-09", "2019-03", "2019-09", "2020-03", "2020-09", "2021-03", "2021-09", "2022-03", "2022-09", "2023-03", "2023-09", "2024-03", "2024-09", "2025-03", "2025-09", "2025-10"], "sectors": ["Financial Services", "Automobile and Auto Components", "Capital Goods", "Consumer Durables", "Chemicals", "Healthcare", "Consumer Services", "Construction Materials", "Information Technology", "Unclassified", "Other"], "matrix": [[14.9, 14.5, 19.3, 21.5, 22.8, 24.2, 20.2, 19.6, 18.3, 16.4, 18.2, 18.3, 20.9, 19.1, 19.0, 22.8, 21.0, 17.9, 19.5, 23.1, 23.3, 22.0, 20.8, 20.5, 20.7, 21.8], [8.1, 10.4, 13.9, 13.2, 13.1, 13.5, 12.7, 13.0, 14.0, 15.3, 13.6, 12.3, 13.0, 13.5, 11.0, 9.0, 5.7, 5.5, 7.3, 6.8, 5.4, 6.5, 7.0, 6.6, 7.4, 6.7], [11.7, 13.4, 10.1, 8.6, 6.5, 5.6, 6.7, 5.6, 5.2, 8.3, 10.3, 9.9, 9.8, 6.5, 8.8, 8.7, 8.2, 8.1, 11.4, 12.7, 12.6, 12.2, 9.2, 9.0, 12.3, 12.5], [5.2, 4.6, 3.9, 7.2, 8.1, 8.7, 10.2, 11.4, 11.7, 14.1, 11.0, 10.0, 10.1, 10.9, 12.5, 12.6, 12.9, 12.2, 8.8, 7.1, 6.4, 7.5, 9.8, 7.0, 4.8, 5.1], [11.4, 9.0, 7.5, 7.7, 5.7, 4.8, 4.9, 4.8, 5.1, 6.4, 7.2, 8.8, 8.7, 7.6, 7.6, 8.3, 7.4, 8.2, 7.4, 6.1, 6.3, 5.6, 7.1, 8.0, 6.9, 6.3], [14.8, 5.9, 5.5, 6.4, 6.7, 4.8, 4.3, 4.6, 5.2, 4.8, 5.0, 4.4, 3.2, 3.4, 2.4, 5.3, 5.0, 7.7, 8.2, 7.2, 7.9, 8.8, 10.0, 11.4, 11.2, 10.0], [0.0, 0.0, 1.1, 1.4, 2.9, 2.0, 1.5, 3.8, 4.5, 6.5, 7.5, 7.6, 8.2, 7.9, 8.6, 7.8, 9.6, 10.2, 11.1, 8.0, 6.0, 6.4, 5.2, 6.1, 5.5, 5.3], [1.5, 4.1, 4.2, 3.5, 3.0, 2.5, 2.8, 2.4, 2.1, 3.5, 4.1, 4.6, 5.0, 5.2, 8.1, 6.6, 6.6, 5.6, 5.5, 5.4, 5.3, 4.8, 3.8, 5.0, 3.8, 3.7], [1.2, 3.1, 3.3, 4.0, 3.6, 2.4, 1.1, 2.9, 3.3, 1.3, 0.0, 0.0, 0.0, 1.2, 1.0, 2.3, 4.7, 7.0, 4.4, 5.2, 6.0, 5.7, 6.0, 6.2, 5.7, 6.1], [17.9, 15.4, 14.4, 13.7, 14.6, 14.3, 17.4, 15.1, 12.2, 7.2, 10.3, 11.2, 7.7, 8.4, 4.7, 5.5, 6.6, 5.6, 5.2, 4.1, 4.0, 3.1, 2.1, 0.8, 1.9, 1.5], [13.3, 19.6, 16.8, 12.9, 13.0, 17.2, 18.2, 16.9, 18.4, 16.2, 12.5, 13.0, 13.3, 16.4, 16.2, 11.2, 12.4, 12.0, 11.2, 14.4, 17.0, 17.4, 19.0, 19.4, 19.9, 21.1]]}, "conc_ts": [{"ym": "2013-09", "top10": 42.8, "n": 49}, {"ym": "2014-03", "top10": 34.8, "n": 57}, {"ym": "2014-09", "top10": 31.2, "n": 61}, {"ym": "2015-03", "top10": 31.5, "n": 59}, {"ym": "2015-09", "top10": 30.2, "n": 57}, {"ym": "2016-03", "top10": 31.2, "n": 57}, {"ym": "2016-09", "top10": 33.8, "n": 54}, {"ym": "2017-03", "top10": 29.3, "n": 61}, {"ym": "2017-09", "top10": 28.9, "n": 61}, {"ym": "2018-03", "top10": 29.0, "n": 58}, {"ym": "2018-09", "top10": 29.5, "n": 57}, {"ym": "2019-03", "top10": 28.7, "n": 61}, {"ym": "2019-09", "top10": 30.5, "n": 61}, {"ym": "2020-03", "top10": 31.0, "n": 61}, {"ym": "2020-09", "top10": 33.0, "n": 50}, {"ym": "2021-03", "top10": 33.4, "n": 50}, {"ym": "2021-09", "top10": 34.7, "n": 50}, {"ym": "2022-03", "top10": 31.8, "n": 62}, {"ym": "2022-09", "top10": 30.2, "n": 65}, {"ym": "2023-03", "top10": 28.8, "n": 67}, {"ym": "2023-09", "top10": 26.7, "n": 67}, {"ym": "2024-03", "top10": 25.5, "n": 71}, {"ym": "2024-09", "top10": 23.4, "n": 76}, {"ym": "2025-03", "top10": 22.5, "n": 81}, {"ym": "2025-09", "top10": 21.4, "n": 86}, {"ym": "2025-10", "top10": 22.0, "n": 86}]}}